Workbook

Sheet Pro Forma
A1: ARKANSAS INNOVATION HUB COOPERATIVE
A2: FINANCIAL PRO FORMA - 1
A3: Prepared: December 30, 2025
A5: Line Item | B5: Total | C5: Jan | D5: Feb | E5: Mar | F5: Apr | G5: May | H5: Jun | I5: Jul | J5: Aug | K5: Sep | L5: Oct | M5: Nov | N5: Dec
A7: REVENUE
A9: Total Membership Revenue | B9: =SUM(C9:N9) -> 202275 | C9: ='Revenue Projection'!C9 -> 11775 | D9: ='Revenue Projection'!D9 -> 13410 | E9: ='Revenue Projection'!E9 -> 15420 | F9: ='Revenue Projection'!F9 -> 17030 | G9: ='Revenue Projection'!G9 -> 17430 | H9: ='Revenue Projection'!H9 -> 17430 | I9: ='Revenue Projection'!I9 -> 17830 | J9: ='Revenue Projection'!J9 -> 17830 | ... N9: ='Revenue Projection'!N9 -> 19030
A10: Total Education/Fabrication Revenue | B10: =SUM(C10:N10) -> 216730.96 | C10: ='Revenue Projection'!C152 -> 0 | D10: ='Revenue Projection'!D152 -> 0 | E10: ='Revenue Projection'!E152 -> 0 | F10: ='Revenue Projection'!F152 -> 25125.12 | G10: ='Revenue Projection'!G152 -> 25905.12 | H10: ='Revenue Projection'!H152 -> 25455.12 | I10: ='Revenue Projection'!I152 -> 23025.12 | J10: ='Revenue Projection'!J152 -> 19681.56 | ... N10: ='Revenue Projection'!N152 -> 20227.12
A12: TOTAL EARNED INCOME | B12: =SUM(C12:N12) -> 419005.96 | C12: =C9+C10 -> 11775 | D12: =D9+D10 -> 13410 | E12: =E9+E10 -> 15420 | F12: =F9+F10 -> 42155.12 | G12: =G9+G10 -> 43335.12 | H12: =H9+H10 -> 42885.12 | I12: =I9+I10 -> 40855.12 | J12: =J9+J10 -> 37511.56 | ... N12: =N9+N10 -> 39257.12
A14: Grant Revenue (Separate Programs)
A15: Skills to Launch Grant | B15: =SUM(C15:N15) -> 114996 | C15: 9583 | D15: 9583 | E15: 9583 | F15: 9583 | G15: 9583 | H15: 9583 | I15: 9583 | J15: 9583 | K15: 9583 | L15: 9583 | M15: 9583 | N15: 9583
A16: Best Buy Teen Tech Center | B16: =SUM(C16:N16) -> 69996 | C16: 5833 | D16: 5833 | E16: 5833 | F16: 5833 | G16: 5833 | H16: 5833 | I16: 5833 | J16: 5833 | K16: 5833 | L16: 5833 | M16: 5833 | N16: 5833
A17: Microsoft TechSpark | B17: =SUM(C17:N17) -> 50004 | C17: 4167 | D17: 4167 | E17: 4167 | F17: 4167 | G17: 4167 | H17: 4167 | I17: 4167 | J17: 4167 | K17: 4167 | L17: 4167 | M17: 4167 | N17: 4167
A18: Grant Overhead Contribution (10%) | B18: =SUM(C18:N18) -> 23499.6 | C18: =SUM(C15:C17)*0.1 -> 1958.3 | D18: =SUM(D15:D17)*0.1 -> 1958.3 | E18: =SUM(E15:E17)*0.1 -> 1958.3 | F18: =SUM(F15:F17)*0.1 -> 1958.3 | G18: =SUM(G15:G17)*0.1 -> 1958.3 | H18: =SUM(H15:H17)*0.1 -> 1958.3 | I18: =SUM(I15:I17)*0.1 -> 1958.3 | J18: =SUM(J15:J17)*0.1 -> 1958.3 | ... N18: =SUM(N15:N17)*0.1 -> 1958.3
A20: Support (Foundation/Corporate/Fundraiser) | B20: =SUM(C20:N20) -> 153768 | C20: 12814 | D20: 12814 | E20: 12814 | F20: 12814 | G20: 12814 | H20: 12814 | I20: 12814 | J20: 12814 | K20: 12814 | L20: 12814 | M20: 12814 | N20: 12814
A22: TOTAL REVENUE | B22: =SUM(C22:N22) -> 831269.56 | C22: =sum(C15:C20)+C12 -> 46130.3 | D22: =sum(D15:D20)+D12 -> 47765.3 | E22: =sum(E15:E20)+E12 -> 49775.3 | F22: =sum(F15:F20)+F12 -> 76510.42 | G22: =sum(G15:G20)+G12 -> 77690.42 | H22: =sum(H15:H20)+H12 -> 77240.42 | I22: =sum(I15:I20)+I12 -> 75210.42 | J22: =sum(J15:J20)+J12 -> 71866.86 | ... N22: =sum(N15:N20)+N12 -> 73612.42
A24: EXPENSES
A25: Core Personnel (Non-Grant)
A26: Executive Director (Level 4) | B26: =SUM(C26:N26) -> 102180 | C26: =Staffing!I9 -> 8515 | D26: =Staffing!I9 -> 8515 | E26: =Staffing!I9 -> 8515 | F26: =Staffing!I9 -> 8515 | G26: =Staffing!I9 -> 8515 | H26: =Staffing!I9 -> 8515 | I26: =Staffing!I9 -> 8515 | J26: =Staffing!I9 -> 8515 | K26: =Staffing!I9 -> 8515 | L26: =Staffing!I9 -> 8515 | M26: =Staffing!I9 -> 8515 | N26: =Staffing!I9 -> 8515
A27: Maker Educators (4 @ Level 2) | B27: =SUM(C27:N27) -> 199080 | C27: 0 | D27: 0 | E27: 0 | F27: =Staffing!G9*4 -> 22120 | G27: =Staffing!G9*4 -> 22120 | H27: =Staffing!G9*4 -> 22120 | I27: =Staffing!G9*4 -> 22120 | J27: =Staffing!G9*4 -> 22120 | K27: =Staffing!G9*4 -> 22120 | L27: =Staffing!G9*4 -> 22120 | M27: =Staffing!G9*4 -> 22120 | N27: =Staffing!G9*4 -> 22120
A28: Member Services & Outreach (Level 2) | B28: =SUM(C28:N28) -> 66360 | C28: =Staffing!G9 -> 5530 | D28: =Staffing!G9 -> 5530 | E28: =Staffing!G9 -> 5530 | F28: =Staffing!G9 -> 5530 | G28: =Staffing!G9 -> 5530 | H28: =Staffing!G9 -> 5530 | I28: =Staffing!G9 -> 5530 | J28: =Staffing!G9 -> 5530 | K28: =Staffing!G9 -> 5530 | L28: =Staffing!G9 -> 5530 | M28: =Staffing!G9 -> 5530 | N28: =Staffing!G9 -> 5530
A29: Total Core Personnel | B29: =SUM(C29:N29) -> 367620 | C29: =SUM(C26:C28) -> 14045 | D29: =SUM(D26:D28) -> 14045 | E29: =SUM(E26:E28) -> 14045 | F29: =SUM(F26:F28) -> 36165 | G29: =SUM(G26:G28) -> 36165 | H29: =SUM(H26:H28) -> 36165 | I29: =SUM(I26:I28) -> 36165 | J29: =SUM(J26:J28) -> 36165 | ... N29: =SUM(N26:N28) -> 36165
A31: Grant-Funded Personnel & Expenses
A32: Skills to Launch | B32: =SUM(C32:N32) -> 114996 | C32: =C15 -> 9583 | D32: =D15 -> 9583 | E32: =E15 -> 9583 | F32: =F15 -> 9583 | G32: =G15 -> 9583 | H32: =H15 -> 9583 | I32: =I15 -> 9583 | J32: =J15 -> 9583 | ... N32: =N15 -> 9583
A33: Best Buy Teen Tech Staff | B33: =SUM(C33:N33) -> 69996 | C33: =C16 -> 5833 | D33: =D16 -> 5833 | E33: =E16 -> 5833 | F33: =F16 -> 5833 | G33: =G16 -> 5833 | H33: =H16 -> 5833 | I33: =I16 -> 5833 | J33: =J16 -> 5833 | ... N33: =N16 -> 5833
A34: Microsoft TechSpark Coordinator | B34: =SUM(C34:N34) -> 50004 | C34: =C17 -> 4167 | D34: =D17 -> 4167 | E34: =E17 -> 4167 | F34: =F17 -> 4167 | G34: =G17 -> 4167 | H34: =H17 -> 4167 | I34: =I17 -> 4167 | J34: =J17 -> 4167 | ... N34: =N17 -> 4167
A35: Total Grant Personnel | B35: =SUM(C35:N35) -> 234996 | C35: =SUM(C32:C34) -> 19583 | D35: =SUM(D32:D34) -> 19583 | E35: =SUM(E32:E34) -> 19583 | F35: =SUM(F32:F34) -> 19583 | G35: =SUM(G32:G34) -> 19583 | H35: =SUM(H32:H34) -> 19583 | I35: =SUM(I32:I34) -> 19583 | J35: =SUM(J32:J34) -> 19583 | ... N35: =SUM(N32:N34) -> 19583
A37: Facilities & Operations
A38: Utilities (Electric, Gas, Water) | B38: =SUM(C38:N38) -> 30000 | C38: 2500 | D38: 2500 | E38: 2500 | F38: 2500 | G38: 2500 | H38: 2500 | I38: 2500 | J38: 2500 | K38: 2500 | L38: 2500 | M38: 2500 | N38: 2500
A39: Internet & Phone | B39: =SUM(C39:N39) -> 6000 | C39: 500 | D39: 500 | E39: 500 | F39: 500 | G39: 500 | H39: 500 | I39: 500 | J39: 500 | K39: 500 | L39: 500 | M39: 500 | N39: 500
A40: Insurance (Property, Liability, Equipment) | B40: =SUM(C40:N40) -> 15000 | C40: 1250 | D40: 1250 | E40: 1250 | F40: 1250 | G40: 1250 | H40: 1250 | I40: 1250 | J40: 1250 | K40: 1250 | L40: 1250 | M40: 1250 | N40: 1250
A41: Maintenance & Repairs | B41: =SUM(C41:N41) -> 12000 | C41: 1000 | D41: 1000 | E41: 1000 | F41: 1000 | G41: 1000 | H41: 1000 | I41: 1000 | J41: 1000 | K41: 1000 | L41: 1000 | M41: 1000 | N41: 1000
A42: Supplies & Materials | B42: =SUM(C42:N42) -> 18000 | C42: 1500 | D42: 1500 | E42: 1500 | F42: 1500 | G42: 1500 | H42: 1500 | I42: 1500 | J42: 1500 | K42: 1500 | L42: 1500 | M42: 1500 | N42: 1500
A43: Equipment Maintenance & Upgrades | B43: =SUM(C43:N43) -> 9996 | C43: 833 | D43: 833 | E43: 833 | F43: 833 | G43: 833 | H43: 833 | I43: 833 | J43: 833 | K43: 833 | L43: 833 | M43: 833 | N43: 833
A44: Total Facilities & Operations | B44: =SUM(C44:N44) -> 90996 | C44: =SUM(C38:C43) -> 7583 | D44: =SUM(D38:D43) -> 7583 | E44: =SUM(E38:E43) -> 7583 | F44: =SUM(F38:F43) -> 7583 | G44: =SUM(G38:G43) -> 7583 | H44: =SUM(H38:H43) -> 7583 | I44: =SUM(I38:I43) -> 7583 | J44: =SUM(J38:J43) -> 7583 | ... N44: =SUM(N38:N43) -> 7583
A46: Debt Service (Property & Equipment Loan)
A47: CDFI Loan Payment | B47: =SUM(C47:N47) -> 75000 | C47: 6250 | D47: 6250 | E47: 6250 | F47: 6250 | G47: 6250 | H47: 6250 | I47: 6250 | J47: 6250 | K47: 6250 | L47: 6250 | M47: 6250 | N47: 6250
A49: Program & Marketing
A50: Marketing & Outreach | B50: =SUM(C50:N50) -> 6000 | C50: 500 | D50: 500 | E50: 500 | F50: 500 | G50: 500 | H50: 500 | I50: 500 | J50: 500 | K50: 500 | L50: 500 | M50: 500 | N50: 500
A51: Total Program & Marketing | B51: =SUM(C51:N51) -> 6000 | C51: =SUM(C50) -> 500 | D51: =SUM(D50) -> 500 | E51: =SUM(E50) -> 500 | F51: =SUM(F50) -> 500 | G51: =SUM(G50) -> 500 | H51: =SUM(H50) -> 500 | I51: =SUM(I50) -> 500 | J51: =SUM(J50) -> 500 | ... N51: =SUM(N50) -> 500
A53: Administrative & Professional
A54: Accounting & Bookkeeping | B54: =SUM(C54:N54) -> 5004 | C54: 417 | D54: 417 | E54: 417 | F54: 417 | G54: 417 | H54: 417 | I54: 417 | J54: 417 | K54: 417 | L54: 417 | M54: 417 | N54: 417
A55: Legal & Compliance | B55: =SUM(C55:N55) -> 3000 | C55: 250 | D55: 250 | E55: 250 | F55: 250 | G55: 250 | H55: 250 | I55: 250 | J55: 250 | K55: 250 | L55: 250 | M55: 250 | N55: 250
A56: Software & Technology | B56: =SUM(C56:N56) -> 3000 | C56: 250 | D56: 250 | E56: 250 | F56: 250 | G56: 250 | H56: 250 | I56: 250 | J56: 250 | K56: 250 | L56: 250 | M56: 250 | N56: 250
A57: Office Supplies & Misc | B57: =SUM(C57:N57) -> 2004 | C57: 167 | D57: 167 | E57: 167 | F57: 167 | G57: 167 | H57: 167 | I57: 167 | J57: 167 | K57: 167 | L57: 167 | M57: 167 | N57: 167
A58: Total Administrative | B58: =SUM(C58:N58) -> 13008 | C58: =SUM(C54:C57) -> 1084 | D58: =SUM(D54:D57) -> 1084 | E58: =SUM(E54:E57) -> 1084 | F58: =SUM(F54:F57) -> 1084 | G58: =SUM(G54:G57) -> 1084 | H58: =SUM(H54:H57) -> 1084 | I58: =SUM(I54:I57) -> 1084 | J58: =SUM(J54:J57) -> 1084 | ... N58: =SUM(N54:N57) -> 1084
A60: TOTAL EXPENSES | B60: =SUM(C60:N60) -> 787620 | C60: =C29+C35+C44+C47+C51+C58 -> 49045 | D60: =D29+D35+D44+D47+D51+D58 -> 49045 | E60: =E29+E35+E44+E47+E51+E58 -> 49045 | F60: =F29+F35+F44+F47+F51+F58 -> 71165 | G60: =G29+G35+G44+G47+G51+G58 -> 71165 | H60: =H29+H35+H44+H47+H51+H58 -> 71165 | I60: =I29+I35+I44+I47+I51+I58 -> 71165 | J60: =J29+J35+J44+J47+J51+J58 -> 71165 | ... N60: =N29+N35+N44+N47+N51+N58 -> 71165
A62: NET INCOME / (LOSS) | B62: =SUM(C62:N62) -> 43649.56 | C62: =C22-C60 -> -2914.7 | D62: =D22-D60 -> -1279.7 | E62: =E22-E60 -> 730.3 | F62: =F22-F60 -> 5345.42 | G62: =G22-G60 -> 6525.42 | H62: =H22-H60 -> 6075.42 | I62: =I22-I60 -> 4045.42 | J62: =J22-J60 -> 701.86 | ... N62: =N22-N60 -> 2447.42
A64: CASH FLOW | B64: END OF YEAR | C64: Jan | D64: Feb | E64: Mar | F64: Apr | G64: May | H64: Jun | I64: Jul | J64: Aug | K64: Sep | L64: Oct | M64: Nov | N64: Dec
A65: Beginning Balance | C65: 250000 | D65: =C66 -> 247085.3 | E65: =D66 -> 245805.6 | F65: =E66 -> 246535.9 | G65: =F66 -> 251881.32 | H65: =G66 -> 258406.74 | I65: =H66 -> 264482.16 | J65: =I66 -> 268527.58 | K65: =J66 -> 269229.44 | ... N65: =M66 -> 291202.14
A66: Ending Balance | B66: =N66 -> 293649.56 | C66: =C65+C62 -> 247085.3 | D66: =D65+D62 -> 245805.6 | E66: =E65+E62 -> 246535.9 | F66: =F65+F62 -> 251881.32 | G66: =G65+G62 -> 258406.74 | H66: =H65+H62 -> 264482.16 | I66: =I65+I62 -> 268527.58 | J66: =J65+J62 -> 269229.44 | ... N66: =N65+N62 -> 293649.56

Sheet Revenue Projection
A1: REVENUE STREAM CALCULATOR
A2: Membership Tier | B2: Monthly Fee | C2: Jan | D2: Feb | E2: Mar | F2: Apr | G2: May | H2: Jun | I2: Jul | J2: Aug | K2: Sep | L2: Oct | M2: Nov | N2: Dec
A3: Voting Members | B3: 80 | C3: 50 | D3: 55 | E3: 60 | F3: 65 | G3: 65 | H3: 65 | I3: 65 | J3: 65 | K3: 65 | L3: 65 | M3: 65 | N3: 65
A4: Supporting Members | B4: 50 | C4: 100 | D4: 120 | E4: 140 | F4: 160 | G4: 160 | H4: 160 | I4: 160 | J4: 160 | K4: 160 | L4: 160 | M4: 160 | N4: 160
A5: Family Members | B5: 80 | C5: 20 | D5: 22 | E5: 24 | F5: 26 | G5: 26 | H5: 26 | I5: 26 | J5: 26 | K5: 26 | L5: 26 | M5: 26 | N5: 26
A6: Student Members | B6: 25 | C6: 15 | D6: 18 | E6: 20 | F6: 22 | G6: 22 | H6: 22 | I6: 22 | J6: 22 | K6: 22 | L6: 22 | M6: 22 | N6: 22
A7: Corporate Members | B7: 400 | C7: 2 | D7: 2 | E7: 3 | F7: 3 | G7: 4 | H7: 4 | I7: 5 | J7: 5 | K7: 6 | L7: 6 | M7: 7 | N7: 8
A8: Total Member | C8: =sum(C3:C7) -> 187 | D8: =sum(D3:D7) -> 217 | E8: =sum(E3:E7) -> 247 | F8: =sum(F3:F7) -> 276 | G8: =sum(G3:G7) -> 277 | H8: =sum(H3:H7) -> 277 | I8: =sum(I3:I7) -> 278 | J8: =sum(J3:J7) -> 278 | ... N8: =sum(N3:N7) -> 281
A9: Total Membership Revenue | C9: =sum((C3*B3)+(C4*B4)+(C5*B5)+(C6*B6)+(C7*B7)) -> 11775 | D9: =sum((D3*B3)+(D4*B4)+(D5*B5)+(D6*B6)+(D7*B7)) -> 13410 | E9: =sum((E3*B3)+(E4*B4)+(E5*B5)+(E6*B6)+(E7*B7)) -> 15420 | F9: =sum((F3*B3)+(F4*B4)+(F5*B5)+(F6*B6)+(F7*B7)) -> 17030 | G9: =sum((G3*B3)+(G4*B4)+(G5*B5)+(G6*B6)+(G7*B7)) -> 17430 | H9: =sum((H3*B3)+(H4*B4)+(H5*B5)+(H6*B6)+(H7*B7)) -> 17430 | I9: =sum((I3*B3)+(I4*B4)+(I5*B5)+(I6*B6)+(I7*B7)) -> 17830 | J9: =sum((J3*B3)+(J4*B4)+(J5*B5)+(J6*B6)+(J7*B7)) -> 17830 | K9: =sum((K3*B3)+(K4*B4)+(K5*B5)+(K6*B6)+(K7*B7)) -> 18230 | L9: =sum((L3*B3)+(L4*B4)+(L5*B5)+(L6*B6)+(L7*B7)) -> 18230 | M9: =sum((M3*B3)+(M4*B4)+(M5*B5)+(M6*B6)+(M7*B7)) -> 18630 | N9: =sum((N3*B3)+(N4*B4)+(N5*B5)+(N6*B6)+(N7*B7)) -> 19030
A11: ADULT CLASSES | C11: Jan | D11: Feb | E11: Mar | F11: Apr | G11: May | H11: Jun | I11: Jul | J11: Aug | K11: Sep | L11: Oct | M11: Nov | N11: Dec
A12: INPUT PARAMETERS | B12: Notes
A13: Total classes | B13: Weekend + weeknight + intensives combined | C13: 0 | D13: 0 | E13: 0 | F13: 30 | G13: 30 | H13: 30 | I13: 30 | J13: 30 | K13: 30 | L13: 30 | M13: 30 | N13: 12
A14: Average students per class | B14: Weighted average across all class types | C14: 9 | D14: 9 | E14: 9 | F14: 9 | G14: 9 | H14: 9 | I14: 9 | J14: 9 | K14: 9 | L14: 9 | M14: 9 | N14: 9
A15: Average price per student | B15: Typical tuition per student per class | C15: 65 | D15: 65 | E15: 65 | F15: 65 | G15: 65 | H15: 65 | I15: 65 | J15: 65 | K15: 65 | L15: 65 | M15: 65 | N15: 65
A16: Average class duration (hours) | B16: Instructional time per class | C16: 3 | D16: 3 | E16: 3 | F16: 3 | G16: 3 | H16: 3 | I16: 3 | J16: 3 | K16: 3 | L16: 3 | M16: 3 | N16: 3
A17: Average prep time per class (hours) | B17: Setup, planning, cleanup per class | C17: 1 | D17: 1 | E17: 1 | F17: 1 | G17: 1 | H17: 1 | I17: 1 | J17: 1 | K17: 1 | L17: 1 | M17: 1 | N17: 1
A18: Materials % of revenue | B18: Supplies and consumables | C18: 0.1 | D18: 0.1 | E18: 0.1 | F18: 0.1 | G18: 0.1 | H18: 0.1 | I18: 0.1 | J18: 0.1 | K18: 0.1 | L18: 0.1 | M18: 0.1 | N18: 0.1
A19: Instructor share % of revenue | B19: Revenue share paid to instructors | C19: 0.3 | D19: 0.3 | E19: 0.3 | F19: 0.3 | G19: 0.3 | H19: 0.3 | I19: 0.3 | J19: 0.3 | K19: 0.3 | L19: 0.3 | M19: 0.3 | N19: 0.3
A21: CALCULATED RESULTS
A22: Total Students Served | C22: =C13*C14 -> 0 | D22: =D13*D14 -> 0 | E22: =E13*E14 -> 0 | F22: =F13*F14 -> 270 | G22: =G13*G14 -> 270 | H22: =H13*H14 -> 270 | I22: =I13*I14 -> 270 | J22: =J13*J14 -> 270 | ... N22: =N13*N14 -> 108
A23: Gross Revenue | C23: =C13*C14*C15 -> 0 | D23: =D13*D14*D15 -> 0 | E23: =E13*E14*E15 -> 0 | F23: =F13*F14*F15 -> 17550 | G23: =G13*G14*G15 -> 17550 | H23: =H13*H14*H15 -> 17550 | I23: =I13*I14*I15 -> 17550 | J23: =J13*J14*J15 -> 17550 | ... N23: =N13*N14*N15 -> 7020
A24: Less: Materials Cost | C24: =C23*C18 -> 0 | D24: =D23*D18 -> 0 | E24: =E23*E18 -> 0 | F24: =F23*F18 -> 1755 | G24: =G23*G18 -> 1755 | H24: =H23*H18 -> 1755 | I24: =I23*I18 -> 1755 | J24: =J23*J18 -> 1755 | ... N24: =N23*N18 -> 702
A25: Less: Instructor Share | C25: =C23*C19 -> 0 | D25: =D23*D19 -> 0 | E25: =E23*E19 -> 0 | F25: =F23*F19 -> 5265 | G25: =G23*G19 -> 5265 | H25: =H23*H19 -> 5265 | I25: =I23*I19 -> 5265 | J25: =J23*J19 -> 5265 | ... N25: =N23*N19 -> 2106
A26: NET TO HUB | C26: =C23-C24-C25 -> 0 | D26: =D23-D24-D25 -> 0 | E26: =E23-E24-E25 -> 0 | F26: =F23-F24-F25 -> 10530 | G26: =G23-G24-G25 -> 10530 | H26: =H23-H24-H25 -> 10530 | I26: =I23-I24-I25 -> 10530 | J26: =J23-J24-J25 -> 10530 | ... N26: =N23-N24-N25 -> 4212
A28: FTE ANALYSIS
A29: Total hours per class | C29: =C16+C17 -> 4 | D29: =D16+D17 -> 4 | E29: =E16+E17 -> 4 | F29: =F16+F17 -> 4 | G29: =G16+G17 -> 4 | H29: =H16+H17 -> 4 | I29: =I16+I17 -> 4 | J29: =J16+J17 -> 4 | ... N29: =N16+N17 -> 4
A30: hours required | C30: =C13*C29 -> 0 | D30: =D13*D29 -> 0 | E30: =E13*E29 -> 0 | F30: =F13*F29 -> 120 | G30: =G13*G29 -> 120 | H30: =H13*H29 -> 120 | I30: =I13*I29 -> 120 | J30: =J13*J29 -> 120 | ... N30: =N13*N29 -> 48
A31: FTE REQUIRED (160 hrs/mo) | C31: =C30/160 -> 0 | D31: =D30/160 -> 0 | E31: =E30/160 -> 0 | F31: =F30/160 -> 0.75 | G31: =G30/160 -> 0.75 | H31: =H30/160 -> 0.75 | I31: =I30/160 -> 0.75 | J31: =J30/160 -> 0.75 | ... N31: =N30/160 -> 0.3
A32: REVENUE PER FTE | C32: =C26/C31 -> #DIV/0! | D32: =D26/D31 -> #DIV/0! | E32: =E26/E31 -> #DIV/0! | F32: =F26/F31 -> 14040 | G32: =G26/G31 -> 14040 | H32: =H26/H31 -> 14040 | I32: =I26/I31 -> 14040 | J32: =J26/J31 -> 14040 | ... N32: =N26/N31 -> 14040
A35: YOUTH/FAMILY PROGRAMS | C35: Jan | D35: Feb | E35: Mar | F35: Apr | G35: May | H35: Jun | I35: Jul | J35: Aug | K35: Sep | L35: Oct | M35: Nov | N35: Dec
A36: INPUT PARAMETERS | B36: Notes
A37: Total programs per | B37: Workshops + camps + parent-child combined | C37: 0 | D37: 0 | E37: 0 | F37: 8 | G37: 8 | H37: 8 | I37: 8 | J37: 8 | K37: 8 | L37: 8 | M37: 8 | N37: 8
A38: Average participants per program | B38: Weighted average across all program types | C38: 11 | D38: 11 | E38: 11 | F38: 11 | G38: 11 | H38: 11 | I38: 11 | J38: 11 | K38: 11 | L38: 11 | M38: 11 | N38: 11
A39: Average price per participant | B39: Typical tuition per participant | C39: 65 | D39: 65 | E39: 65 | F39: 65 | G39: 65 | H39: 65 | I39: 65 | J39: 65 | K39: 65 | L39: 65 | M39: 65 | N39: 65
A40: Average program duration (hours) | B40: Weighted avg: workshops 2.5h, camps 20h | C40: 4 | D40: 4 | E40: 4 | F40: 4 | G40: 4 | H40: 4 | I40: 4 | J40: 4 | K40: 4 | L40: 4 | M40: 4 | N40: 4
A41: Average prep time (hours) | B41: Setup, planning, cleanup | C41: 1.5 | D41: 1.5 | E41: 1.5 | F41: 1.5 | G41: 1.5 | H41: 1.5 | I41: 1.5 | J41: 1.5 | K41: 1.5 | L41: 1.5 | M41: 1.5 | N41: 1.5
A42: Materials % of revenue | B42: Supplies and consumables | C42: 0.3 | D42: 0.3 | E42: 0.3 | F42: 0.3 | G42: 0.3 | H42: 0.3 | I42: 0.3 | J42: 0.3 | K42: 0.3 | L42: 0.3 | M42: 0.3 | N42: 0.3
A43: Instructor share % of revenue | B43: Revenue share to instructors | C43: 0.3 | D43: 0.3 | E43: 0.3 | F43: 0.3 | G43: 0.3 | H43: 0.3 | I43: 0.3 | J43: 0.3 | K43: 0.3 | L43: 0.3 | M43: 0.3 | N43: 0.3
A45: CALCULATED RESULTS
A46: Total Participants Served | C46: =C37*C38 -> 0 | D46: =D37*D38 -> 0 | E46: =E37*E38 -> 0 | F46: =F37*F38 -> 88 | G46: =G37*G38 -> 88 | H46: =H37*H38 -> 88 | I46: =I37*I38 -> 88 | J46: =J37*J38 -> 88 | ... N46: =N37*N38 -> 88
A47: Gross Revenue | C47: =C37*C38*C39 -> 0 | D47: =D37*D38*D39 -> 0 | E47: =E37*E38*E39 -> 0 | F47: =F37*F38*F39 -> 5720 | G47: =G37*G38*G39 -> 5720 | H47: =H37*H38*H39 -> 5720 | I47: =I37*I38*I39 -> 5720 | J47: =J37*J38*J39 -> 5720 | ... N47: =N37*N38*N39 -> 5720
A48: Less: Materials Cost | C48: =C47*C42 -> 0 | D48: =D47*D42 -> 0 | E48: =E47*E42 -> 0 | F48: =F47*F42 -> 1716 | G48: =G47*G42 -> 1716 | H48: =H47*H42 -> 1716 | I48: =I47*I42 -> 1716 | J48: =J47*J42 -> 1716 | ... N48: =N47*N42 -> 1716
A49: Less: Instructor Share | C49: =C47*C43 -> 0 | D49: =D47*D43 -> 0 | E49: =E47*E43 -> 0 | F49: =F47*F43 -> 1716 | G49: =G47*G43 -> 1716 | H49: =H47*H43 -> 1716 | I49: =I47*I43 -> 1716 | J49: =J47*J43 -> 1716 | ... N49: =N47*N43 -> 1716
A50: NET TO HUB | C50: =C47-C48-C49 -> 0 | D50: =D47-D48-D49 -> 0 | E50: =E47-E48-E49 -> 0 | F50: =F47-F48-F49 -> 2288 | G50: =G47-G48-G49 -> 2288 | H50: =H47-H48-H49 -> 2288 | I50: =I47-I48-I49 -> 2288 | J50: =J47-J48-J49 -> 2288 | ... N50: =N47-N48-N49 -> 2288
A52: FTE ANALYSIS
A53: Total hours per program | C53: =C40+C41 -> 5.5 | D53: =D40+D41 -> 5.5 | E53: =E40+E41 -> 5.5 | F53: =F40+F41 -> 5.5 | G53: =G40+G41 -> 5.5 | H53: =H40+H41 -> 5.5 | I53: =I40+I41 -> 5.5 | J53: =J40+J41 -> 5.5 | ... N53: =N40+N41 -> 5.5
A54: hours required | C54: =C37*C53 -> 0 | D54: =D37*D53 -> 0 | E54: =E37*E53 -> 0 | F54: =F37*F53 -> 44 | G54: =G37*G53 -> 44 | H54: =H37*H53 -> 44 | I54: =I37*I53 -> 44 | J54: =J37*J53 -> 44 | ... N54: =N37*N53 -> 44
A55: FTE REQUIRED (160 hrs/mo) | C55: =C54/160 -> 0 | D55: =D54/160 -> 0 | E55: =E54/160 -> 0 | F55: =F54/160 -> 0.275 | G55: =G54/160 -> 0.275 | H55: =H54/160 -> 0.275 | I55: =I54/160 -> 0.275 | J55: =J54/160 -> 0.275 | ... N55: =N54/160 -> 0.275
A56: REVENUE PER FTE | C56: =C50/C55 -> #DIV/0! | D56: =D50/D55 -> #DIV/0! | E56: =E50/E55 -> #DIV/0! | F56: =F50/F55 -> 8320 | G56: =G50/G55 -> 8320 | H56: =H50/H55 -> 8320 | I56: =I50/I55 -> 8320 | J56: =J50/J55 -> 8320 | ... N56: =N50/N55 -> 8320
A59: SCHOOL FIELD TRIPS | C59: Jan | D59: Feb | E59: Mar | F59: Apr | G59: May | H59: Jun | I59: Jul | J59: Aug | K59: Sep | L59: Oct | M59: Nov | N59: Dec
A60: INPUT PARAMETERS | B60: Notes
A61: Field trips per | B61: September through June (school ) | C61: 0 | D61: 0 | E61: 0 | F61: 7 | G61: 8 | H61: 5 | I61: 0 | J61: 0 | K61: 8 | L61: 9 | M61: 11 | N61: 7
A62: Average students per trip | B62: Typical class size for schools | C62: 24 | D62: 24 | E62: 24 | F62: 24 | G62: 24 | H62: 24 | I62: 24 | J62: 24 | K62: 24 | L62: 24 | M62: 24 | N62: 24
A63: Price per student | B63: Charged to school/district | C63: 15 | D63: 15 | E63: 15 | F63: 15 | G63: 15 | H63: 15 | I63: 15 | J63: 15 | K63: 15 | L63: 15 | M63: 15 | N63: 15
A64: Duration per trip (hours) | B64: Hands-on activity time | C64: 2 | D64: 2 | E64: 2 | F64: 2 | G64: 2 | H64: 2 | I64: 2 | J64: 2 | K64: 2 | L64: 2 | M64: 2 | N64: 2
A65: Prep/cleanup per trip (hours) | B65: Setup before & after | C65: 0.5 | D65: 0.5 | E65: 0.5 | F65: 0.5 | G65: 0.5 | H65: 0.5 | I65: 0.5 | J65: 0.5 | K65: 0.5 | L65: 0.5 | M65: 0.5 | N65: 0.5
A66: Materials % of revenue | B66: Covered in base supplies budget | C66: 0 | D66: 0 | E66: 0 | F66: 0 | G66: 0 | H66: 0 | I66: 0 | J66: 0 | K66: 0 | L66: 0 | M66: 0 | N66: 0
A67: Instructor share % of revenue | B67: Maker Educators (salaried staff) | C67: 0 | D67: 0 | E67: 0 | F67: 0 | G67: 0 | H67: 0 | I67: 0 | J67: 0 | K67: 0 | L67: 0 | M67: 0 | N67: 0
A69: CALCULATED RESULTS
A70: Total Students Served | C70: =C61*C62 -> 0 | D70: =D61*D62 -> 0 | E70: =E61*E62 -> 0 | F70: =F61*F62 -> 168 | G70: =G61*G62 -> 192 | H70: =H61*H62 -> 120 | I70: =I61*I62 -> 0 | J70: =J61*J62 -> 0 | ... N70: =N61*N62 -> 168
A71: Gross Revenue | C71: =C61*C62*C63 -> 0 | D71: =D61*D62*D63 -> 0 | E71: =E61*E62*E63 -> 0 | F71: =F61*F62*F63 -> 2520 | G71: =G61*G62*G63 -> 2880 | H71: =H61*H62*H63 -> 1800 | I71: =I61*I62*I63 -> 0 | J71: =J61*J62*J63 -> 0 | ... N71: =N61*N62*N63 -> 2520
A72: Less: Materials Cost | C72: =C71*C66 -> 0 | D72: =D71*D66 -> 0 | E72: =E71*E66 -> 0 | F72: =F71*F66 -> 0 | G72: =G71*G66 -> 0 | H72: =H71*H66 -> 0 | I72: =I71*I66 -> 0 | J72: =J71*J66 -> 0 | ... N72: =N71*N66 -> 0
A73: Less: Instructor Share | C73: =C71*C67 -> 0 | D73: =D71*D67 -> 0 | E73: =E71*E67 -> 0 | F73: =F71*F67 -> 0 | G73: =G71*G67 -> 0 | H73: =H71*H67 -> 0 | I73: =I71*I67 -> 0 | J73: =J71*J67 -> 0 | ... N73: =N71*N67 -> 0
A74: NET TO HUB | C74: =C71-C72-C73 -> 0 | D74: =D71-D72-D73 -> 0 | E74: =E71-E72-E73 -> 0 | F74: =F71-F72-F73 -> 2520 | G74: =G71-G72-G73 -> 2880 | H74: =H71-H72-H73 -> 1800 | I74: =I71-I72-I73 -> 0 | J74: =J71-J72-J73 -> 0 | ... N74: =N71-N72-N73 -> 2520
A76: FTE ANALYSIS
A77: Total hours per trip | C77: =C64+C65 -> 2.5 | D77: =D64+D65 -> 2.5 | E77: =E64+E65 -> 2.5 | F77: =F64+F65 -> 2.5 | G77: =G64+G65 -> 2.5 | H77: =H64+H65 -> 2.5 | I77: =I64+I65 -> 2.5 | J77: =J64+J65 -> 2.5 | ... N77: =N64+N65 -> 2.5
A78: hours required | C78: =C61*C77 -> 0 | D78: =D61*D77 -> 0 | E78: =E61*E77 -> 0 | F78: =F61*F77 -> 17.5 | G78: =G61*G77 -> 20 | H78: =H61*H77 -> 12.5 | I78: =I61*I77 -> 0 | J78: =J61*J77 -> 0 | ... N78: =N61*N77 -> 17.5
A79: FTE REQUIRED (160 hrs/mo) | C79: =C78/160 -> 0 | D79: =D78/160 -> 0 | E79: =E78/160 -> 0 | F79: =F78/160 -> 0.109375 | G79: =G78/160 -> 0.125 | H79: =H78/160 -> 0.078125 | I79: =I78/160 -> 0 | J79: =J78/160 -> 0 | ... N79: =N78/160 -> 0.109375
A80: REVENUE PER FTE | C80: =C74/C79 -> #DIV/0! | D80: =D74/D79 -> #DIV/0! | E80: =E74/E79 -> #DIV/0! | F80: =F74/F79 -> 23040 | G80: =G74/G79 -> 23040 | H80: =H74/H79 -> 23040 | I80: =I74/I79 -> #DIV/0! | J80: =J74/J79 -> #DIV/0! | ... N80: =N74/N79 -> 23040
A83: ARKANSAS LEARNS / EFA PROGRAMMING | C83: Jan | D83: Feb | E83: Mar | F83: Apr | G83: May | H83: Jun | I83: Jul | J83: Aug | K83: Sep | L83: Oct | M83: Nov | N83: Dec
A84: INPUT PARAMETERS | B84: Notes
A85: Total programs per | B85: Semester courses (8) + workshops (24) + memberships (12 mo) | C85: 0 | D85: 0 | E85: 0 | F85: 8 | G85: 8 | H85: 8 | I85: 8 | J85: 4 | K85: 4 | L85: 8 | M85: 8 | N85: 8
A86: Average students per program | B86: Weighted: courses 10, workshops 8, families 15 | C86: 11 | D86: 11 | E86: 11 | F86: 11 | G86: 11 | H86: 11 | I86: 11 | J86: 11 | K86: 11 | L86: 11 | M86: 11 | N86: 11
A87: Average price per student | B87: Weighted: courses $400, workshops $60, membership $50/mo | C87: 102 | D87: 102 | E87: 102 | F87: 102 | G87: 102 | H87: 102 | I87: 102 | J87: 102 | K87: 102 | L87: 102 | M87: 102 | N87: 102
A88: Average hours per program | B88: Weighted: courses 42h, workshops 4h, membership 4.5h | C88: 10 | D88: 10 | E88: 10 | F88: 10 | G88: 10 | H88: 10 | I88: 10 | J88: 10 | K88: 10 | L88: 10 | M88: 10 | N88: 10
A89: Materials % of revenue | B89: Consumables and supplies | C89: 0.065 | D89: 0.065 | E89: 0.065 | F89: 0.065 | G89: 0.065 | H89: 0.065 | I89: 0.065 | J89: 0.065 | K89: 0.065 | L89: 0.065 | M89: 0.065 | N89: 0.065
A90: Instructor share % of revenue | B90: Weighted: 30% on courses only, 0% workshops/membership | C90: 0.19 | D90: 0.19 | E90: 0.19 | F90: 0.19 | G90: 0.19 | H90: 0.19 | I90: 0.19 | J90: 0.19 | K90: 0.19 | L90: 0.19 | M90: 0.19 | N90: 0.19
A92: CALCULATED RESULTS
A93: Total Students Served | C93: =C85*C86 -> 0 | D93: =D85*D86 -> 0 | E93: =E85*E86 -> 0 | F93: =F85*F86 -> 88 | G93: =G85*G86 -> 88 | H93: =H85*H86 -> 88 | I93: =I85*I86 -> 88 | J93: =J85*J86 -> 44 | ... N93: =N85*N86 -> 88
A94: Gross Revenue | C94: =C85*C86*C87 -> 0 | D94: =D85*D86*D87 -> 0 | E94: =E85*E86*E87 -> 0 | F94: =F85*F86*F87 -> 8976 | G94: =G85*G86*G87 -> 8976 | H94: =H85*H86*H87 -> 8976 | I94: =I85*I86*I87 -> 8976 | J94: =J85*J86*J87 -> 4488 | ... N94: =N85*N86*N87 -> 8976
A95: Less: Materials Cost | C95: =C94*C89 -> 0 | D95: =D94*D89 -> 0 | E95: =E94*E89 -> 0 | F95: =F94*F89 -> 583.44 | G95: =G94*G89 -> 583.44 | H95: =H94*H89 -> 583.44 | I95: =I94*I89 -> 583.44 | J95: =J94*J89 -> 291.72 | ... N95: =N94*N89 -> 583.44
A96: Less: Instructor Share | C96: =C94*C90 -> 0 | D96: =D94*D90 -> 0 | E96: =E94*E90 -> 0 | F96: =F94*F90 -> 1705.44 | G96: =G94*G90 -> 1705.44 | H96: =H94*H90 -> 1705.44 | I96: =I94*I90 -> 1705.44 | J96: =J94*J90 -> 852.72 | ... N96: =N94*N90 -> 1705.44
A97: NET TO HUB | C97: =C94-C95-C96 -> 0 | D97: =D94-D95-D96 -> 0 | E97: =E94-E95-E96 -> 0 | F97: =F94-F95-F96 -> 6687.12 | G97: =G94-G95-G96 -> 6687.12 | H97: =H94-H95-H96 -> 6687.12 | I97: =I94-I95-I96 -> 6687.12 | J97: =J94-J95-J96 -> 3343.56 | ... N97: =N94-N95-N96 -> 6687.12
A99: FTE ANALYSIS
A100: hours required | C100: =C85*C88 -> 0 | D100: =D85*D88 -> 0 | E100: =E85*E88 -> 0 | F100: =F85*F88 -> 80 | G100: =G85*G88 -> 80 | H100: =H85*H88 -> 80 | I100: =I85*I88 -> 80 | J100: =J85*J88 -> 40 | ... N100: =N85*N88 -> 80
A101: FTE REQUIRED (160 hrs/mo) | C101: =C100/160 -> 0 | D101: =D100/160 -> 0 | E101: =E100/160 -> 0 | F101: =F100/160 -> 0.5 | G101: =G100/160 -> 0.5 | H101: =H100/160 -> 0.5 | I101: =I100/160 -> 0.5 | J101: =J100/160 -> 0.25 | ... N101: =N100/160 -> 0.5
A102: REVENUE PER FTE | C102: =C97/C101 -> #DIV/0! | D102: =D97/D101 -> #DIV/0! | E102: =E97/E101 -> #DIV/0! | F102: =F97/F101 -> 13374.24 | G102: =G97/G101 -> 13374.24 | H102: =H97/H101 -> 13374.24 | I102: =I97/I101 -> 13374.24 | J102: =J97/J101 -> 13374.24 | ... N102: =N97/N101 -> 13374.24
A105: FABRICATION SERVICES | C105: Jan | D105: Feb | E105: Mar | F105: Apr | G105: May | H105: Jun | I105: Jul | J105: Aug | K105: Sep | L105: Oct | M105: Nov | N105: Dec
A106: INPUT PARAMETERS | B106: Notes
A107: Projects per | B107: Custom fabrication, prototypes, production runs | C107: 0 | D107: 0 | E107: 0 | F107: 10 | G107: 12 | H107: 15 | I107: 12 | J107: 12 | K107: 12 | L107: 12 | M107: 12 | N107: 12
A108: Average project value | B108: Typical project invoice amount | C108: 350 | D108: 350 | E108: 350 | F108: 350 | G108: 350 | H108: 350 | I108: 350 | J108: 350 | K108: 350 | L108: 350 | M108: 350 | N108: 350
A109: Average hours per project | B109: Consultation + setup + run time | C109: 4 | D109: 4 | E109: 4 | F109: 4 | G109: 4 | H109: 4 | I109: 4 | J109: 4 | K109: 4 | L109: 4 | M109: 4 | N109: 4
A110: Materials % of revenue | B110: Wood, acrylic, filament, hardware, etc. | C110: 0.4 | D110: 0.4 | E110: 0.4 | F110: 0.4 | G110: 0.4 | H110: 0.4 | I110: 0.4 | J110: 0.4 | K110: 0.4 | L110: 0.4 | M110: 0.4 | N110: 0.4
A111: Tech/Instructor share % of revenue | B111: Maker Educators (salaried staff) | C111: 0 | D111: 0 | E111: 0 | F111: 0 | G111: 0 | H111: 0 | I111: 0 | J111: 0 | K111: 0 | L111: 0 | M111: 0 | N111: 0
A113: CALCULATED RESULTS
A114: Gross Revenue | C114: =C107*C108 -> 0 | D114: =D107*D108 -> 0 | E114: =E107*E108 -> 0 | F114: =F107*F108 -> 3500 | G114: =G107*G108 -> 4200 | H114: =H107*H108 -> 5250 | I114: =I107*I108 -> 4200 | J114: =J107*J108 -> 4200 | ... N114: =N107*N108 -> 4200
A115: Less: Materials Cost | C115: =C114*C110 -> 0 | D115: =D114*D110 -> 0 | E115: =E114*E110 -> 0 | F115: =F114*F110 -> 1400 | G115: =G114*G110 -> 1680 | H115: =H114*H110 -> 2100 | I115: =I114*I110 -> 1680 | J115: =J114*J110 -> 1680 | ... N115: =N114*N110 -> 1680
A116: Less: Tech/Instructor Share | C116: =C114*C111 -> 0 | D116: =D114*D111 -> 0 | E116: =E114*E111 -> 0 | F116: =F114*F111 -> 0 | G116: =G114*G111 -> 0 | H116: =H114*H111 -> 0 | I116: =I114*I111 -> 0 | J116: =J114*J111 -> 0 | ... N116: =N114*N111 -> 0
A117: NET TO HUB | C117: =C114-C115-C116 -> 0 | D117: =D114-D115-D116 -> 0 | E117: =E114-E115-E116 -> 0 | F117: =F114-F115-F116 -> 2100 | G117: =G114-G115-G116 -> 2520 | H117: =H114-H115-H116 -> 3150 | I117: =I114-I115-I116 -> 2520 | J117: =J114-J115-J116 -> 2520 | ... N117: =N114-N115-N116 -> 2520
A119: FTE ANALYSIS
...

Sheet Staffing
A1: Actual Hours | E1: Part-time | F1: Level 1 | G1: Level 2 | H1: Level 3 | I1: Level 4
A2: Paid Vacation (2 weeks) | B2: 80 | D2: Salary | E2: 30000 | F2: 40000 | G2: 45000 | H2: 55000 | I2: 75000
A3: Paid Sick Leave (8 days) | B3: 56 | D3: Insurance | E3: 0 | F3: =F2*B13 -> 2600 | G3: =G2*B13 -> 2925 | H3: =H2*B13 -> 3575 | I3: =I2*B13 -> 4875
A4: Paid Company Holidays (8 Federal US Holidays/Year) | B4: 56 | D4: Withholding/Taxes | E4: =E2*B19 -> 3270 | F4: =F2*B19 -> 4360 | G4: =G2*B19 -> 4905 | H4: =H2*B19 -> 5995 | I4: =I2*B19 -> 8175
A5: Total Non-Productive Hours (15 min per workday) | B5: 59 | D5: Benefits | E5: 0 | F5: =B28 -> 10500 | G5: =B28 -> 10500 | H5: =B28 -> 10500 | I5: =B28 -> 10500
A6: Total Leave Hours: | B6: 251 | D6: 401k | E6: 0 | F6: =F2*B23 -> 800 | G6: =G2*B23 -> 900 | H6: =H2*B23 -> 1100 | I6: =I2*B23 -> 1500
A7: Total Paid Hours (8 hrs/Day, 5 days/week, 52 weeks/ year): | B7: 2080 | D7: Office Expenses | E7: =B40 -> 2130 | F7: =B40 -> 2130 | G7: =B40 -> 2130 | H7: =B40 -> 2130 | I7: =B40 -> 2130
A8: Total Actual Work Hours (2080 – 251) | B8: 1829 | D8: Total | E8: =SUM(E2:E7) -> 35400 | F8: =SUM(F2:F7) -> 60390 | G8: =SUM(G2:G7) -> 66360 | H8: =SUM(H2:H7) -> 78300 | I8: =SUM(I2:I7) -> 102180
D9: Monthly Cost | E9: =E8/12 -> 2950 | F9: =F8/12 -> 5032.5 | G9: =G8/12 -> 5530 | H9: =H8/12 -> 6525 | I9: =I8/12 -> 8515
A10: Insurance | D10: Weekly Cost | E10: =E8/52 -> 680.76923 | F10: =F8/52 -> 1161.3462 | G10: =G8/52 -> 1276.1538 | H10: =H8/52 -> 1505.7692 | I10: =I8/52 -> 1965
A11: Workers Compensation Insurances (Rates vary widely on this) | B11: 0.045 | D11: Hourly Cost | E11: =E8/B8 -> 19.354839 | F11: =F8/B8 -> 33.018043 | G11: =G8/B8 -> 36.282121 | H11: =H8/B8 -> 42.810279 | I11: =I8/B8 -> 55.866594
A12: Liability Insurance (Often Billed as a % of Labor) | B12: 0.02 | D12: 60% markup billable hour rate | E12: =E11*1.6 -> 30.967742 | F12: =F11*1.6 -> 52.828868 | G12: =G11*1.6 -> 58.051394 | H12: =H11*1.6 -> 68.496446 | I12: =I11*1.6 -> 89.38655
B13: =SUM(B11:B12) -> 0.065 | D13: Break Even Hours Monthly | E13: =E9/E12 -> 95.260417 | F13: =F9/F12 -> 95.260417 | G13: =G9/G12 -> 95.260417 | H13: =H9/H12 -> 95.260417 | I13: =I9/I12 -> 95.260417
D14: Break Even Hours Weekly | E14: =E10/E12 -> 21.983173 | F14: =F10/F12 -> 21.983173 | G14: =G10/G12 -> 21.983173 | H14: =H10/H12 -> 21.983173 | I14: =I10/I12 -> 21.983173
A15: Withholding/Taxes
A16: FICA (Medicate / Social Security) | B16: 0.0765 | D16: Experiance Level | E16: 0 | F16: <1 | G16: 44200 | H16: 44292 | I16: 6+
A17: FUTA (Federal Unemployment Tax Act) | B17: 0.0035
A18: State Unemployment | B18: 0.029
B19: =SUM(B16:B18) -> 0.109
A22: Benefits
A23: 401K (Company Contribution Portion) | B23: 0.02
A24: Training | B24: 5000
A25: Health/Medical Insurance | B25: 3000
A26: Meals & Travel Reimbursement | B26: 1500
A27: Christmas Bonus | B27: 1000
B28: =SUM(B24:B27) -> 10500
A30: Office Expenses
A31: Equipment 100 monthly BYOD | B31: 1200
A32: Office Space (including internet & utilities) | B32: 0
A33: Parking | B33: 0
A34: G-Suite | B34: =25*12 -> 300
A35: Zoom | B35: 0
A36: AntiVirus | B36: =25*12 -> 300
A37: Payroll/Benefits Software Fee | B37: =20*12 -> 240
A38: Security Clearance ?
A39: Background Check | B39: 90
B40: =SUM(B31:B39) -> 2130
A43: Tools
A44: Payroll | C44: 12 | D44: $39 base fee + $12 per person a month
A45: Communications & Security | B45: Gsuites | C45: 12 | D45: $12 per person a month
A46: Accounting | B46: Quickbooks | C46: 90 | D46: $90 a month
A47: Total Office Software | B47: Monthly | C47: =SUM(C44:C46) -> 114
